[
    {
        "recType": "ROUTER",
        "identity": "t5zgd:0",
        "parent": "6d449c84-6f6c-4eac-aa5e-bedfbbf467a7",
        "startTime": 1658260724486801,
        "name": "0/public1-skupper-router-677797d595-t5zgd",
        "namespace": "mongo-public1",
        "imageName": "skupper-router",
        "imageVersion": "latest",
        "hostame": "skupper-router-677797d595-t5zgd",
        "buildVersion": "UNKNOWN"
    },
    {
        "recType": "ROUTER",
        "identity": "wr4pc:0",
        "parent": "5f54ee36-54ac-4002-8f2d-691a06b25d47",
        "startTime": 1658260732268932,
        "name": "0/public2-skupper-router-c99749f74-wr4pc",
        "namespace": "mongo-public2",
        "imageName": "skupper-router",
        "imageVersion": "latest",
        "hostame": "skupper-router-c99749f74-wr4pc",
        "buildVersion": "UNKNOWN"
    },
    {
        "recType": "ROUTER",
        "identity": "59tnd:0",
        "parent": "bfc21843-16fb-4c19-a4cc-c5938bc96768",
        "startTime": 1658260708487233,
        "name": "0/private-skupper-router-56455d7598-59tnd",
        "namespace": "mongo-private",
        "imageName": "skupper-router",
        "imageVersion": "latest",
        "hostame": "skupper-router-56455d7598-59tnd",
        "buildVersion": "UNKNOWN"
    }
]
